flask_security/__init__.py
flask_security/babel.py
flask_security/change_email.py
flask_security/changeable.py
flask_security/cli.py
flask_security/confirmable.py
flask_security/core.py
flask_security/datastore.py
flask_security/decorators.py
flask_security/forms.py
flask_security/json.py
flask_security/mail_util.py
flask_security/oauth_glue.py
flask_security/oauth_provider.py
flask_security/password_util.py
flask_security/passwordless.py
flask_security/phone_util.py
flask_security/proxies.py
flask_security/py.typed
flask_security/quart_compat.py
flask_security/recoverable.py
flask_security/recovery_codes.py
flask_security/registerable.py
flask_security/signals.py
flask_security/tf_plugin.py
flask_security/totp.py
flask_security/twofactor.py
flask_security/unified_signin.py
flask_security/username_util.py
flask_security/utils.py
flask_security/views.py
flask_security/webauthn.py
flask_security/webauthn_util.py
flask_security/models/__init__.py
flask_security/models/fsqla.py
flask_security/models/fsqla_v2.py
flask_security/models/fsqla_v3.py
flask_security/models/sqla.py
flask_security/static/js/base64.js
flask_security/static/js/webauthn.js
flask_security/templates/security/_macros.html
flask_security/templates/security/_menu.html
flask_security/templates/security/_messages.html
flask_security/templates/security/base.html
flask_security/templates/security/change_email.html
flask_security/templates/security/change_password.html
flask_security/templates/security/forgot_password.html
flask_security/templates/security/login_user.html
flask_security/templates/security/mf_recovery.html
flask_security/templates/security/mf_recovery_codes.html
flask_security/templates/security/register_user.html
flask_security/templates/security/reset_password.html
flask_security/templates/security/send_confirmation.html
flask_security/templates/security/send_login.html
flask_security/templates/security/two_factor_select.html
flask_security/templates/security/two_factor_setup.html
Flask_Security_Too-5.5.0.dist-info/AUTHORS
Flask_Security_Too-5.5.0.dist-info/LICENSE
Flask_Security_Too-5.5.0.dist-info/METADATA
Flask_Security_Too-5.5.0.dist-info/WHEEL
Flask_Security_Too-5.5.0.dist-info/top_level.txt
Flask_Security_Too-5.5.0.dist-info/RECORD
