Metadata-Version: 2.1
Name: Flask-Security-Too
Version: 5.5.0
Summary: Quickly add security features to your Flask application.
Author: Matt Wright
Author-email: Chris Wagner <jwag.wagner+github@gmail.com>
Maintainer-email: Chris Wagner <jwag.wagner+github@gmail.com>
Project-URL: Documentation, https://flask-security-too.readthedocs.io
Project-URL: Homepage, https://github.com/Flask-Middleware/flask-security
Project-URL: Source, https://github.com/Flask-Middleware/flask-security
Project-URL: Tracker, https://github.com/Flask-Middleware/flask-security/issues
Project-URL: Releases, https://pypi.org/project/Flask-Security-Too/
Keywords: flask security
Classifier: Environment :: Web Environment
Classifier: Framework :: Flask
Classifier: Intended Audience :: Developers
Classifier: License :: OSI Approved :: MIT License
Classifier: Operating System :: OS Independent
Classifier: Programming Language :: Python
Classifier: Topic :: Internet :: WWW/HTTP :: Dynamic Content
Classifier: Topic :: Software Development :: Libraries :: Python Modules
Classifier: Programming Language :: Python :: 3
Classifier: Programming Language :: Python :: 3.9
Classifier: Programming Language :: Python :: 3.10
Classifier: Programming Language :: Python :: 3.11
Classifier: Programming Language :: Python :: 3.12
Classifier: Programming Language :: Python :: Implementation :: CPython
Classifier: Programming Language :: Python :: Implementation :: PyPy
Classifier: Development Status :: 5 - Production/Stable
Requires-Python: >=3.9
License-File: LICENSE
License-File: AUTHORS
Requires-Dist: Flask>=3.0.0
Requires-Dist: Flask-Login>=0.6.3
Requires-Dist: Flask-Principal>=0.4.0
Requires-Dist: Flask-WTF>=1.1.2
Requires-Dist: email-validator>=2.0.0
Requires-Dist: markupsafe>=2.1.0
Requires-Dist: passlib>=1.7.4
Requires-Dist: wtforms>=3.0.0
Requires-Dist: importlib_resources>=5.10.0
Provides-Extra: babel
Requires-Dist: babel>=2.12.1; extra == "babel"
Requires-Dist: flask_babel>=3.1.0; extra == "babel"
Provides-Extra: fsqla
Requires-Dist: flask_sqlalchemy>=3.1.0; extra == "fsqla"
Requires-Dist: sqlalchemy>=2.0.18; extra == "fsqla"
Requires-Dist: sqlalchemy-utils>=0.41.1; extra == "fsqla"
Provides-Extra: common
Requires-Dist: argon2_cffi>=21.3.0; extra == "common"
Requires-Dist: bcrypt>=4.0.1; extra == "common"
Requires-Dist: flask_mailman>=0.3.0; extra == "common"
Requires-Dist: bleach>=6.0.0; extra == "common"
Provides-Extra: mfa
Requires-Dist: cryptography>=40.0.2; extra == "mfa"
Requires-Dist: qrcode>=7.4.2; extra == "mfa"
Requires-Dist: phonenumberslite>=8.13.11; extra == "mfa"
Requires-Dist: webauthn>=2.0.0; extra == "mfa"
Provides-Extra: low
Requires-Dist: Flask==3.0.0; extra == "low"
Requires-Dist: Flask-SQLAlchemy==3.1.0; extra == "low"
Requires-Dist: Flask-SQLAlchemy-Lite==0.1.0; python_version >= "3.10" and extra == "low"
Requires-Dist: Flask-Babel==3.1.0; extra == "low"
Requires-Dist: Flask-Mailman==0.3.0; extra == "low"
Requires-Dist: Flask-Login==0.6.3; extra == "low"
Requires-Dist: Flask-WTF==1.1.2; extra == "low"
Requires-Dist: peewee==3.16.2; extra == "low"
Requires-Dist: argon2_cffi==21.3.0; extra == "low"
Requires-Dist: authlib==1.2.0; extra == "low"
Requires-Dist: babel==2.12.1; extra == "low"
Requires-Dist: bcrypt==4.0.1; extra == "low"
Requires-Dist: bleach==6.0.0; extra == "low"
Requires-Dist: freezegun; extra == "low"
Requires-Dist: jinja2==3.1.2; extra == "low"
Requires-Dist: itsdangerous==2.1.2; extra == "low"
Requires-Dist: markupsafe==2.1.2; extra == "low"
Requires-Dist: mongoengine==0.27.0; extra == "low"
Requires-Dist: mongomock==4.1.2; extra == "low"
Requires-Dist: pony==0.7.16; python_version < "3.11" and extra == "low"
Requires-Dist: phonenumberslite==8.13.11; extra == "low"
Requires-Dist: qrcode==7.4.2; extra == "low"
Requires-Dist: requests; extra == "low"
Requires-Dist: setuptools; extra == "low"
Requires-Dist: sqlalchemy==2.0.18; extra == "low"
Requires-Dist: sqlalchemy-utils==0.41.1; extra == "low"
Requires-Dist: webauthn==2.0.0; extra == "low"
Requires-Dist: werkzeug==3.0.1; extra == "low"
Requires-Dist: zxcvbn==4.4.28; extra == "low"
